{
    "/js/app.js": "/js/app.js",
    "/css/app.css": "/css/app.css",
    "/js/chats.js": "/js/chats.js",
    "/js/chats.ef560b67ea9722bad696.hot-update.js": "/js/chats.ef560b67ea9722bad696.hot-update.js",
    "/js/chats.b7271dc79317c650251c.hot-update.js": "/js/chats.b7271dc79317c650251c.hot-update.js",
    "/js/chats.884fdaef57896eda52c4.hot-update.js": "/js/chats.884fdaef57896eda52c4.hot-update.js",
    "/js/chats.7e1246a77af4d9d965cc.hot-update.js": "/js/chats.7e1246a77af4d9d965cc.hot-update.js",
    "/js/chats.e78b75972d7c0aefdb11.hot-update.js": "/js/chats.e78b75972d7c0aefdb11.hot-update.js",
    "/js/chats.933dfeb114068bb1b471.hot-update.js": "/js/chats.933dfeb114068bb1b471.hot-update.js",
    "/js/chats.b5b27372e46a63552f55.hot-update.js": "/js/chats.b5b27372e46a63552f55.hot-update.js",
    "/js/chats.0f6cf534dfce3c8dac4e.hot-update.js": "/js/chats.0f6cf534dfce3c8dac4e.hot-update.js",
    "/js/chats.6b9f19068ba1892a222f.hot-update.js": "/js/chats.6b9f19068ba1892a222f.hot-update.js",
    "/js/chats.2b4c85da3197b4ac0dee.hot-update.js": "/js/chats.2b4c85da3197b4ac0dee.hot-update.js",
    "/js/chats.183dd40dcfbef58dffd9.hot-update.js": "/js/chats.183dd40dcfbef58dffd9.hot-update.js",
    "/js/chats.ad937f7070b0b2412c7a.hot-update.js": "/js/chats.ad937f7070b0b2412c7a.hot-update.js",
    "/js/chats.f0e2ccf7a0563a2901a0.hot-update.js": "/js/chats.f0e2ccf7a0563a2901a0.hot-update.js",
    "/js/chats.45cedb0f2ff36e1fcef5.hot-update.js": "/js/chats.45cedb0f2ff36e1fcef5.hot-update.js",
    "/js/chats.e2df2048ed9af681e553.hot-update.js": "/js/chats.e2df2048ed9af681e553.hot-update.js"
}
